README.md
setup.py
mlcrl/__init__.py
mlcrl/create_1d_zernike_basis.py
mlcrl/create_1d_zernike_sampled_profiles.py
mlcrl/create_2d_zernike_sampled_profiles.py
mlcrl/create_files_2d_zernike_sampled_profiles.py
mlcrl/get_wofry_data.py
mlcrl.egg-info/PKG-INFO
mlcrl.egg-info/SOURCES.txt
mlcrl.egg-info/dependency_links.txt
mlcrl.egg-info/requires.txt
mlcrl.egg-info/top_level.txt
mlcrl/phasenet/__init__.py
mlcrl/phasenet/model.py
mlcrl/phasenet/noise.py
mlcrl/phasenet/phantoms.py
mlcrl/phasenet/psf.py
mlcrl/phasenet/setup_PHASENET.py
mlcrl/phasenet/utils.py
mlcrl/phasenet/version.py
mlcrl/phasenet/zernike.py