Metadata-Version: 2.1
Name: mlcrl
Version: 0.0.2
Summary: CRLs and more
Home-page: https://github.com/rafaelcelestre/mlcrl/
Author: R. Celestre, J. Reyes Herrera, M. Sanchez del Rio
Author-email: rafael.celestre@esrf.fr
License: UNKNOWN
Platform: UNKNOWN
